tiabio/__init__.py
tiabio/console.py
tiabio/py.typed
tiabio/utils.py
tiabio/keyboard/__init__.py
tiabio/keyboard/keycodes.py
tiabio/keyboard/leds.py
tiabio/keyboard/modifiers.py
tiabio/mouse/__init__.py
tiabio/mouse/buttons.py
tiabio-1.0.0.dist-info/METADATA
tiabio-1.0.0.dist-info/WHEEL
tiabio-1.0.0.dist-info/licenses/LICENSE
tiabio-1.0.0.dist-info/RECORD
