Metadata-Version: 2.4
Name: tiabio
Version: 1.0.0
Summary: Easily interact with the TIAB IO board
Project-URL: homepage, https://codethinklabs.gitlab.io/testing-in-a-box/ct-tiab-documentation/
Project-URL: source, https://gitlab.com/CodethinkLabs/testing-in-a-box/firmware-hardware/tiab-io-board-python.git
Project-URL: issues, https://gitlab.com/CodethinkLabs/testing-in-a-box/firmware-hardware/tiab-io-board-python/-/issues
Author-email: Matthew Howard <matt.howard@codethink.co.uk>
License:                     GNU GENERAL PUBLIC LICENSE
License-File: LICENSE
Keywords: io,testing,tiab
Classifier: License :: OSI Approved :: GNU General Public License v3 (GPLv3)
Classifier: Programming Language :: Python
Requires-Python: >=3.12
Requires-Dist: pyserial>=3.5
Requires-Dist: types-pyserial>=3.5.0.20250304
